setup.py
deepak_packages.egg-info/PKG-INFO
deepak_packages.egg-info/SOURCES.txt
deepak_packages.egg-info/dependency_links.txt
deepak_packages.egg-info/top_level.txt
trainingpack/__init__.py
trainingpack/user_exceptions.py
trainingpack/usertypes.py