Metadata-Version: 1.0
Name: deepak-packages
Version: 1.0.0
Summary: Sample Package
Home-page: UNKNOWN
Author: Deepak
Author-email: abc@xyz.com
License: MIT
Platform: UNKNOWN
